mcp_intercom/__init__.py
mcp_intercom/server.py
mcp_intercom-0.0.3.dist-info/METADATA
mcp_intercom-0.0.3.dist-info/WHEEL
mcp_intercom-0.0.3.dist-info/entry_points.txt
mcp_intercom-0.0.3.dist-info/top_level.txt
mcp_intercom-0.0.3.dist-info/RECORD
