Metadata-Version: 2.4
Name: mcp-intercom
Version: 0.0.3
Summary: MCP server for Intercom integration
Project-URL: Homepage, https://github.com/yourusername/mcp-intercom
Project-URL: Bug Tracker, https://github.com/yourusername/mcp-intercom/issues
Requires-Python: >=3.10
Requires-Dist: mcp[cli]>=1.6.0
Requires-Dist: httpx>=0.24.0
